setup.py
deploycron/__init__.py
deploycron.egg-info/PKG-INFO
deploycron.egg-info/SOURCES.txt
deploycron.egg-info/dependency_links.txt
deploycron.egg-info/top_level.txt
tests/__init__.py